polars_h3-0.6.1.dist-info/METADATA
polars_h3-0.6.1.dist-info/WHEEL
polars_h3-0.6.1.dist-info/licenses/LICENSE
polars_h3/__init__.py
polars_h3/_internal.pyi
polars_h3/core/__init__.py
polars_h3/core/_consts.py
polars_h3/core/_types.py
polars_h3/core/edge.py
polars_h3/core/indexing.py
polars_h3/core/inspection.py
polars_h3/core/metrics.py
polars_h3/core/traversal.py
polars_h3/core/utils.py
polars_h3/core/vertexes.py
polars_h3/graphing.py
polars_h3/polars_h3.abi3.so
polars_h3/typing.py
polars_h3-0.6.1.dist-info/RECORD
