Metadata-Version: 2.4
Name: polars-h3
Version: 0.6.1
Classifier: Programming Language :: Rust
Classifier: Programming Language :: Python :: Implementation :: CPython
Classifier: Programming Language :: Python :: Implementation :: PyPy
License-File: LICENSE
Summary: H3 bindings for Polars
Author-email: Sergey Filimonov <hello@sergey.fyi>
License: MIT
Requires-Python: >=3.9
Project-URL: homepage, https://github.com/filimoa/polars-h3
